{
    "admin": [{
            "address": "mit ghamer",
            "age": "2021-01-05",
            "email": "m@n.com",
            "firstname": "Mahmoud",
            "flag": "1",
            "lastname": "Emam",
            "password": "12345",
            "username": "admin"
        },
        {
            "address": "alex",
            "age": "2020-01-05",
            "email": "mmm@n.com",
            "firstname": "khalid",
            "flag": "1",
            "lastname": "ashraf",
            "password": "67890",
            "username": "m_as"
        }
    ],
    "employees": [{
            "id": "Emp_7h6005ol",
            "absence_times": "1",
            "address": "Mansoura",
            "age": "1997-08-2",
            "attendace_state": "Attend",
            "attendace_time": "3:12:44 AM",
            "attendace_times": "7",
            "email": "m7moud_emam979@gmail.com",
            "excuse_times": "2",
            "firstname": "Mahmoud",
            "flag": "0",
            "lastname": "Emam",
            "late_times": "0",
            "password": "o@18664336601099y_9",
            "today_date": "Thu Feb 11 2021",
            "username": "Emp_7h6005ol"
        },
        {
            "id": "Emp_6a1351hs",
            "absence_times": "2",
            "address": "Cairo",
            "age": "2000-05-20",
            "attendace_state": "Absent",
            "today_date": "Thu Feb 11 2021",
            "attendace_time": "4:05:59 AM",
            "attendace_times": "6",
            "email": "Elmansy@gmail.com",
            "excuse_times": "1",
            "firstname": "Adel",
            "flag": "0",
            "lastname": "Emam",
            "late_times": "1",
            "password": "o@56042351008224n_6",
            "username": "Emp_6a1351hs"
        },
        {
            "id": "Emp_7h3147os",
            "absence_times": "1",
            "address": "Alex",
            "age": "2014-02-20",
            "attendace_state": "Absent",
            "today_date": "Thu Feb 11 2021",
            "attendace_time": "9:59:57 PM",
            "attendace_times": "8",
            "email": "ali@gmail.com",
            "excuse_times": "0",
            "firstname": "Ali",
            "flag": "0",
            "lastname": "Alioy",
            "late_times": "1",
            "password": "o@69384797871193y_6",
            "username": "Emp_7h3147os"
        },
        {
            "id": "Emp_3i8905lb",
            "absence_times": "0",
            "address": "Giza",
            "age": "2021-02-02",
            "attendace_state": "Absent - with Excuse",
            "today_date": "Thu Feb 11 2021",
            "attendace_time": "9:40:47 PM",
            "attendace_times": "9",
            "email": "hema_zahran@gmail.com",
            "excuse_times": "1",
            "firstname": "ibrahim",
            "flag": "0",
            "lastname": "Zahran",
            "late_times": "0",
            "password": "l@63312632059507m_7",
            "username": "Emp_3i8905lb"
        },
        {
            "id": "Emp_7h3147os",
            "absence_times": "1",
            "address": "masna3",
            "age": "2014-02-20",
            "attendace_state": "Absent",
            "today_date": "Thu Feb 11 2021",
            "attendace_time": "9:59:57 PM",
            "attendace_times": "8",
            "email": "ali@gmail.com",
            "excuse_times": "0",
            "firstname": "Tamer",
            "flag": "0",
            "lastname": "maray",
            "late_times": "1",
            "password": "o@69384797871193y_65",
            "username": "Emp_7h3147os5"
        },
        {
            "id": "Emp_3i8905lb",
            "absence_times": "0",
            "address": "Mansoura",
            "age": "2021-02-02",
            "attendace_state": "Absent - with Excuse",
            "today_date": "Thu Feb 11 2021",
            "attendace_time": "9:40:47 PM",
            "attendace_times": "9",
            "email": "hema_zahran@gmail.com",
            "excuse_times": "1",
            "firstname": "Zizo",
            "flag": "0",
            "lastname": "Ntana",
            "late_times": "0",
            "password": "l@63312632059507m_75",
            "username": "Emp_3i8905lb5"
        }
    ]
}